[
  {
    "name": "Zair#Zaza",
    "tier": "DIAMOND",
    "rank": "III",
    "leaguePoints": 20,
    "wins": 24,
    "losses": 25
  },
  {
    "name": "Trastornado#FKC",
    "tier": "DIAMOND",
    "rank": "III",
    "leaguePoints": 59,
    "wins": 46,
    "losses": 25
  },
  {
    "name": "pør casi un G6#FKC",
    "tier": "DIAMOND",
    "rank": "III",
    "leaguePoints": 55,
    "wins": 40,
    "losses": 26
  },
  {
    "name": "Gwungle Account#ARG",
    "tier": "EMERALD",
    "rank": "I",
    "leaguePoints": 78,
    "wins": 34,
    "losses": 29
  },
  {
    "name": "we1rdcat#uwu",
    "tier": "EMERALD",
    "rank": "II",
    "leaguePoints": 43,
    "wins": 23,
    "losses": 26
  },
  {
    "name": "FernecitoConCoca#ARG",
    "tier": "EMERALD",
    "rank": "IV",
    "leaguePoints": 70,
    "wins": 10,
    "losses": 15
  },
  {
    "name": "Tobi Soabe#LAS",
    "tier": "PLATINUM",
    "rank": "III",
    "leaguePoints": 16,
    "wins": 6,
    "losses": 5
  },
  {
    "name": "Lushoto#uwu",
    "tier": "PLATINUM",
    "rank": "IV",
    "leaguePoints": 2,
    "wins": 16,
    "losses": 13
  },
  {
    "name": "Carlos Bianchi#77777",
    "tier": "PLATINUM",
    "rank": "III",
    "leaguePoints": 11,
    "wins": 31,
    "losses": 31
  },
  {
    "name": "Arturo Illia#ARG",
    "tier": "PLATINUM",
    "rank": "IV",
    "leaguePoints": 80,
    "wins": 30,
    "losses": 20
  },
  {
    "name": "GodTDJ#IAN",
    "tier": "GOLD",
    "rank": "I",
    "leaguePoints": 60,
    "wins": 16,
    "losses": 10
  },
  {
    "name": "Aśoka Vardhana#HDS",
    "tier": "SILVER",
    "rank": "I",
    "leaguePoints": 23,
    "wins": 9,
    "losses": 12
  },
  {
    "name": "grande y grueso#7518",
    "tier": "GOLD",
    "rank": "III",
    "leaguePoints": 61,
    "wins": 15,
    "losses": 7
  },
  {
    "name": "ZeeKy#1919",
    "tier": "SILVER",
    "rank": "II",
    "leaguePoints": 62,
    "wins": 17,
    "losses": 25
  },
  {
    "name": "el extraño caso#er9",
    "tier": "SILVER",
    "rank": "I",
    "leaguePoints": 29,
    "wins": 14,
    "losses": 16
  },
  {
    "name": "Gonzaloo0407#LAS",
    "tier": "SILVER",
    "rank": "II",
    "leaguePoints": 90,
    "wins": 9,
    "losses": 6
  },
  {
    "name": "abrilcitauwu#7113",
    "tier": "SILVER",
    "rank": "II",
    "leaguePoints": 40,
    "wins": 15,
    "losses": 8
  },
  {
    "name": "alejandro magno#HDS",
    "tier": "SILVER",
    "rank": "IV",
    "leaguePoints": 79,
    "wins": 11,
    "losses": 12
  },
  {
    "name": "MatiC3#CDE",
    "tier": "UNRANKED",
    "rank": null,
    "leaguePoints": 0,
    "wins": 0,
    "losses": 0
  },
  {
    "name": "Pachu#777",
    "tier": "UNRANKED",
    "rank": null,
    "leaguePoints": 0,
    "wins": 0,
    "losses": 0
  },
  {
    "name": "Samurai Sword#LAS",
    "tier": "UNRANKED",
    "rank": null,
    "leaguePoints": 0,
    "wins": 0,
    "losses": 0
  },
  {
    "name": "Bizkochito#2000",
    "tier": "UNRANKED",
    "rank": null,
    "leaguePoints": 0,
    "wins": 0,
    "losses": 0
  },
  {
    "name": "Chal0#LAS",
    "tier": "PLATINUM",
    "rank": "IV",
    "leaguePoints": 97,
    "wins": 4,
    "losses": 1
  },
  {
    "name": "Rapisher#LAS",
    "tier": "UNRANKED",
    "rank": null,
    "leaguePoints": 0,
    "wins": 0,
    "losses": 0
  },
  {
    "name": "Fl1cka#G2G2",
    "tier": "UNRANKED",
    "rank": null,
    "leaguePoints": 0,
    "wins": 0,
    "losses": 0
  },
  {
    "name": "Mïlls#DHW",
    "tier": "UNRANKED",
    "rank": null,
    "leaguePoints": 0,
    "wins": 0,
    "losses": 0
  }
]